setup.py
txlastfmapi.py
txlastfmapi.egg-info/PKG-INFO
txlastfmapi.egg-info/SOURCES.txt
txlastfmapi.egg-info/dependency_links.txt
txlastfmapi.egg-info/requires.txt
txlastfmapi.egg-info/top_level.txt