Metadata-Version: 1.0
Name: txlastfmapi
Version: 0.1
Summary: A thin wrapper for accessing the Last.fm API with Twisted
Home-page: https://github.com/rockstar/txlastfmapi
Author: Paul Hummer
Author-email: paul@eventuallyanyway.com
License: http://www.opensource.org/licenses/mit-license.php
Keywords: last.fm api twisted asynchronous
Platform: UNKNOWN
